chipipexample/__init__.py
chipipexample/funnel/__init__.py
chipipexample/funnel/helloworld.py
chipipexample-0.1.9.dist-info/METADATA
chipipexample-0.1.9.dist-info/WHEEL
chipipexample-0.1.9.dist-info/top_level.txt
chipipexample-0.1.9.dist-info/RECORD
